ec3/__init__.py
ec3/ec3_api.py
ec3/ec3_categories.py
ec3/ec3_epds.py
ec3/ec3_materials.py
ec3/ec3_projects.py
ec3/ec3_urls.py
ec3/ec3_utils.py
ec3/py.typed
ec3_python_wrapper-0.0.9.dist-info/LICENSE
ec3_python_wrapper-0.0.9.dist-info/METADATA
ec3_python_wrapper-0.0.9.dist-info/WHEEL
ec3_python_wrapper-0.0.9.dist-info/top_level.txt
ec3_python_wrapper-0.0.9.dist-info/RECORD
