Metadata-Version: 2.1
Name: ec3-python-wrapper
Version: 0.0.9
Summary: A python wrapper around the EC3 api by Building Transparency
Home-page: https://github.com/jbf1212/ec3-python-wrapper
Author: Jared Friedman
License: The MIT License (MIT)
Project-URL: Homepage, https://github.com/jbf1212/ec3-python-wrapper
Project-URL: Bug Tracker, https://github.com/jbf1212/ec3-python-wrapper/issues
Keywords: ec3,api
Classifier: Programming Language :: Python :: 3
Classifier: License :: OSI Approved :: MIT License
Classifier: Operating System :: OS Independent
License-File: LICENSE
Requires-Dist: requests (>=2)
Requires-Dist: pgeocode (>=0.3.0)
